LICENSE.md
README.md
setup.cfg
setup.py
src/yeelight_atmosphere/__init__.py
src/yeelight_atmosphere/__main__.py
src/yeelight_atmosphere/bulb.py
src/yeelight_atmosphere/color.py
src/yeelight_atmosphere/const.py
src/yeelight_atmosphere/exception.py
src/yeelight_atmosphere/generator.py
src/yeelight_atmosphere/main.py
src/yeelight_atmosphere/manager.py
src/yeelight_atmosphere.egg-info/PKG-INFO
src/yeelight_atmosphere.egg-info/SOURCES.txt
src/yeelight_atmosphere.egg-info/dependency_links.txt
src/yeelight_atmosphere.egg-info/requires.txt
src/yeelight_atmosphere.egg-info/top_level.txt